icon_generator/__init__.py
icon_generator/iconGen.py
iconGen-0.0.3.dist-info/LICENSE
iconGen-0.0.3.dist-info/METADATA
iconGen-0.0.3.dist-info/WHEEL
iconGen-0.0.3.dist-info/entry_points.txt
iconGen-0.0.3.dist-info/top_level.txt
iconGen-0.0.3.dist-info/RECORD
