Metadata-Version: 2.1
Name: iconGen
Version: 0.0.3
Summary: Handy command line tool with optional GUI to crop and generate icons in different resolutions
Home-page: https://github.com/Madoshakalaka/icon-generator
Author: Matt Yan
Author-email: syan4@ualberta.ca
License: UNKNOWN
Project-URL: Bug Reports, https://github.com/Madoshakalaka/icon-generator/issues
Project-URL: Funding, https://github.com/Madoshakalaka/icon-generator
Project-URL: Say Thanks!, https://github.com/Madoshakalaka/icon-generator
Project-URL: Source, https://github.com/Madoshakalaka/icon-generator
Keywords: icon development
Platform: UNKNOWN
Classifier: Development Status :: 3 - Alpha
Classifier: Intended Audience :: Developers
Classifier: Topic :: Software Development :: Build Tools
Classifier: License :: OSI Approved :: MIT License
Classifier: Programming Language :: Python :: 3
Classifier: Programming Language :: Python :: 3.4
Classifier: Programming Language :: Python :: 3.5
Classifier: Programming Language :: Python :: 3.6
Classifier: Programming Language :: Python :: 3.7
Requires-Python: >=3.5
Requires-Dist: numpy (==1.16.4)
Requires-Dist: opencv-python (==4.1.0.25)
